hklpy2/__init__.py
hklpy2/diffract.py
hklpy2/incident.py
hklpy2/misc.py
hklpy2/ops.py
hklpy2/user.py
hklpy2/backends/__init__.py
hklpy2/backends/base.py
hklpy2/backends/hkl_soleil.py
hklpy2/backends/hkl_soleil_utils.py
hklpy2/backends/no_op.py
hklpy2/backends/th_tth_q.py
hklpy2/backends/tests/__init__.py
hklpy2/backends/tests/test_base.py
hklpy2/backends/tests/test_hkl_soleil.py
hklpy2/backends/tests/test_hkl_soleil_utils.py
hklpy2/backends/tests/test_no_op.py
hklpy2/backends/tests/test_th_tth_q.py
hklpy2/blocks/__init__.py
hklpy2/blocks/configure.py
hklpy2/blocks/constraints.py
hklpy2/blocks/lattice.py
hklpy2/blocks/reflection.py
hklpy2/blocks/sample.py
hklpy2/blocks/tests/__init__.py
hklpy2/blocks/tests/test_configure.py
hklpy2/blocks/tests/test_constraints.py
hklpy2/blocks/tests/test_lattice.py
hklpy2/blocks/tests/test_reflection.py
hklpy2/blocks/tests/test_sample.py
hklpy2/blocks/tests/test_solver.py
hklpy2/tests/__init__.py
hklpy2/tests/common.py
hklpy2/tests/models.py
hklpy2/tests/test_backends.py
hklpy2/tests/test_demo_notebook.py
hklpy2/tests/test_diffract.py
hklpy2/tests/test_e4cv.py
hklpy2/tests/test_incident.py
hklpy2/tests/test_init.py
hklpy2/tests/test_misc.py
hklpy2/tests/test_ops.py
hklpy2/tests/test_tardis.py
hklpy2/tests/test_user.py
hklpy2-0.2.0.dist-info/licenses/LICENSE
hklpy2-0.2.0.dist-info/METADATA
hklpy2-0.2.0.dist-info/WHEEL
hklpy2-0.2.0.dist-info/entry_points.txt
hklpy2-0.2.0.dist-info/top_level.txt
hklpy2-0.2.0.dist-info/RECORD
