Metadata-Version: 2.4
Name: hklpy2
Version: 0.2.0
Summary: 2nd generation controls for diffractometers as PseudoPositioners in the Bluesky Framework.
Author: Bluesky Team
Author-email: Pete Jemian <prjemian+hklpy2@gmail.com>
Maintainer-email: Pete Jemian <prjemian+hklpy2@gmail.com>
License-Expression: LicenseRef-UChicago-Argonne-LLC-License
Project-URL: homepage, https://blueskyproject.io/hklpy2/
Project-URL: issues, https://github.com/bluesky/hklpy2/issues
Project-URL: source, https://github.com/bluesky/hklpy2
Keywords: bluesky,diffraction,diffractometer
Classifier: Development Status :: 3 - Alpha
Classifier: Environment :: Console
Classifier: Environment :: OpenStack
Classifier: Intended Audience :: Science/Research
Classifier: Operating System :: OS Independent
Classifier: Programming Language :: Python :: 3
Classifier: Programming Language :: Python
Classifier: Topic :: Scientific/Engineering
Requires-Python: >=3.10
License-File: LICENSE
Requires-Dist: bluesky_tiled_plugins
Requires-Dist: bluesky
Requires-Dist: cytoolz
Requires-Dist: databroker
Requires-Dist: numpy
Requires-Dist: ophyd
Requires-Dist: pandas
Requires-Dist: pint
Requires-Dist: pyRestTable
Requires-Dist: ruamel.yaml
Requires-Dist: tiled
Requires-Dist: tqdm
Requires-Dist: typeguard
Provides-Extra: dev
Requires-Dist: build; extra == "dev"
Requires-Dist: coverage; extra == "dev"
Requires-Dist: coveralls; extra == "dev"
Requires-Dist: isort; extra == "dev"
Requires-Dist: mypy; extra == "dev"
Requires-Dist: pre-commit; extra == "dev"
Requires-Dist: pytest; extra == "dev"
Requires-Dist: ruff; extra == "dev"
Requires-Dist: bson; extra == "dev"
Requires-Dist: doct; extra == "dev"
Requires-Dist: humanize; extra == "dev"
Requires-Dist: mongomock; extra == "dev"
Requires-Dist: pymongo; extra == "dev"
Requires-Dist: pytest-cov; extra == "dev"
Requires-Dist: pytest-mock; extra == "dev"
Requires-Dist: suitcase-mongo; extra == "dev"
Provides-Extra: doc
Requires-Dist: apstools; extra == "doc"
Requires-Dist: astroid<3.9999; extra == "doc"
Requires-Dist: ipython; extra == "doc"
Requires-Dist: markupsafe; extra == "doc"
Requires-Dist: matplotlib; extra == "doc"
Requires-Dist: myst-nb; extra == "doc"
Requires-Dist: myst-parser; extra == "doc"
Requires-Dist: nbsphinx; extra == "doc"
Requires-Dist: ophyd; extra == "doc"
Requires-Dist: pydata-sphinx-theme; extra == "doc"
Requires-Dist: setuptools>=70.1; extra == "doc"
Requires-Dist: setuptools-scm>=8; extra == "doc"
Requires-Dist: spec2nexus; extra == "doc"
Requires-Dist: sphinx>=7; extra == "doc"
Requires-Dist: sphinx-autoapi; extra == "doc"
Requires-Dist: sphinx-design; extra == "doc"
Requires-Dist: sphinx-tabs; extra == "doc"
Provides-Extra: all
Requires-Dist: hklpy2[dev,doc]; extra == "all"
Dynamic: license-file
